{"cameraMode":{"drawMode":0,"name":"Shaded","section":"Shading Mode"},"sceneLighting":true,"audioPlay":false,"sceneViewState":{"showFog":true,"showMaterialUpdate":false,"showSkybox":true,"showFlares":true,"showImageEffects":true,"showParticleSystems":true},"in2DMode":false,"pivot":{"x":1.536320447921753,"y":3.2533583641052248,"z":-21.574636459350587},"rotation":{"x":-0.05275683477520943,"y":-0.03384919464588165,"z":0.0017896339995786548,"w":-0.9980627298355103},"size":0.30000001192092898,"orthographic":false}